pybatis/__init__.py
pybatis/fastapi.py
pybatis/pybatis.py
pybatis/sql_loader.py
pybatis_neo-0.1.2.dist-info/METADATA
pybatis_neo-0.1.2.dist-info/WHEEL
pybatis_neo-0.1.2.dist-info/licenses/LICENSE
pybatis_neo-0.1.2.dist-info/RECORD
