Metadata-Version: 2.4
Name: pybatis-neo
Version: 0.1.2
Summary: MyBatis-style SQL Mapper for FastAPI - Modern and Pythonic Implementation
Project-URL: Homepage, https://github.com/jinto/pybatis
Project-URL: Documentation, https://pybatis-neo.readthedocs.io
Project-URL: Repository, https://github.com/jinto/pybatis
Project-URL: Issues, https://github.com/jinto/pybatis/issues
Project-URL: Changelog, https://github.com/pybatis/pybatis/blob/main/CHANGELOG.md
Author-email: jinto <jaypark@gmail.com>
Maintainer-email: pyBatis Contributors <jaypark@gmail.com>
License: MIT
License-File: LICENSE
Keywords: async,fastapi,mapper,mybatis,pydantic,sql
Classifier: Development Status :: 4 - Beta
Classifier: Framework :: FastAPI
Classifier: Intended Audience :: Developers
Classifier: License :: OSI Approved :: MIT License
Classifier: Operating System :: OS Independent
Classifier: Programming Language :: Python :: 3
Classifier: Programming Language :: Python :: 3.11
Classifier: Programming Language :: Python :: 3.12
Classifier: Programming Language :: Python :: 3.13
Classifier: Topic :: Database
Classifier: Topic :: Internet :: WWW/HTTP :: Dynamic Content
Classifier: Topic :: Software Development :: Libraries :: Python Modules
Requires-Python: >=3.11
Requires-Dist: fastapi>=0.104.0
Requires-Dist: pydantic>=2.0.0
Requires-Dist: typing-extensions>=4.0.0
Provides-Extra: all
Requires-Dist: aiomysql>=0.2.0; extra == 'all'
Requires-Dist: aiosqlite>=0.19.0; extra == 'all'
Requires-Dist: asyncpg>=0.28.0; extra == 'all'
Provides-Extra: dev
Requires-Dist: black>=23.0.0; extra == 'dev'
Requires-Dist: build>=0.10.0; extra == 'dev'
Requires-Dist: flake8>=6.0.0; extra == 'dev'
Requires-Dist: isort>=5.12.0; extra == 'dev'
Requires-Dist: mypy>=1.0.0; extra == 'dev'
Requires-Dist: pytest-asyncio>=0.21.0; extra == 'dev'
Requires-Dist: pytest-cov>=4.0.0; extra == 'dev'
Requires-Dist: pytest>=7.0.0; extra == 'dev'
Requires-Dist: twine>=4.0.0; extra == 'dev'
Provides-Extra: mysql
Requires-Dist: aiomysql>=0.2.0; extra == 'mysql'
Provides-Extra: postgres
Requires-Dist: asyncpg>=0.28.0; extra == 'postgres'
Provides-Extra: sqlite
Requires-Dist: aiosqlite>=0.19.0; extra == 'sqlite'
